MANIFEST.in
README.rst
setup.py
docs/HISTORY.txt
docs/LICENSE.GPL
docs/LICENSE.txt
docs/screenshot.png
ftw/__init__.py
ftw.calendarwidget.egg-info/PKG-INFO
ftw.calendarwidget.egg-info/SOURCES.txt
ftw.calendarwidget.egg-info/dependency_links.txt
ftw.calendarwidget.egg-info/entry_points.txt
ftw.calendarwidget.egg-info/namespace_packages.txt
ftw.calendarwidget.egg-info/not-zip-safe
ftw.calendarwidget.egg-info/requires.txt
ftw.calendarwidget.egg-info/top_level.txt
ftw/calendarwidget/__init__.py
ftw/calendarwidget/configure.zcml
ftw/calendarwidget/testing.py
ftw/calendarwidget/browser/__init__.py
ftw/calendarwidget/browser/configure.zcml
ftw/calendarwidget/browser/widgets.py
ftw/calendarwidget/browser/resources/ftw_calendar.js
ftw/calendarwidget/profiles/default/jsregistry.xml
ftw/calendarwidget/profiles/default/metadata.xml
ftw/calendarwidget/profiles/default/skins.xml
ftw/calendarwidget/skins/ftw_calendarwidget/ftw_calendar.pt
ftw/calendarwidget/skins/ftw_calendarwidget/picker.pt
ftw/calendarwidget/tests/__init__.py
ftw/calendarwidget/tests/test_integration.py