Metadata-Version: 1.1
Name: ftw.calendarwidget
Version: 1.1.8
Summary: A plone widget for archetypes using the jQuery UI calendar widget
Home-page: https://github.com/4teamwork/ftw.calendarwidget
Author: 4teamwork GmbH
Author-email: mailto:info@4teamwork.ch
License: GPL2
Keywords: ftw calendar widget archetypes plone
Platform: UNKNOWN
Classifier: Framework :: Plone
Classifier: Framework :: Plone :: 4.1
Classifier: Framework :: Plone :: 4.2
Classifier: Framework :: Plone :: 4.3
Classifier: License :: OSI Approved :: GNU General Public License (GPL)
Classifier: Programming Language :: Python
Classifier: Programming Language :: Python :: 2.6
Classifier: Topic :: Software Development :: Libraries :: Python Modules
